{
  "version": "2.0",
  "logging": {
    "applicationInsights": {
      "samplingSettings": {
        "isEnabled": true,
        "excludedTypes": "Request"
      }
    },
    "logLevel": {
      "default": "Information",
      "Host.Results": "Information",
      "Function": "Information",
      "Host.Aggregator": "Information"
    }
  },
  "extensions": {
    "eventHubs": {
      "batchCheckpointFrequency": 5,
      "eventProcessorOptions": {
        "maxBatchSize": 256,
        "prefetchCount": 512
      },
      "initialOffsetOptions": {
        "type": "fromEnqueuedTime",
        "enqueuedTimeUtc": ""
      }
    }
  },
  "functionTimeout": "00:10:00",
  "healthMonitor": {
    "enabled": true,
    "healthCheckInterval": "00:00:10",
    "healthCheckWindow": "00:02:00",
    "healthCheckThreshold": 6,
    "counterThreshold": 0.80
  },
  "extensionBundle": {
    "id": "Microsoft.Azure.Functions.ExtensionBundle",
    "version": "[4.*, 5.0.0)"
  }
}
